setup.py
pdb4amber/__init__.py
pdb4amber/amber_builder.py
pdb4amber/compat.py
pdb4amber/leap_runner.py
pdb4amber/leapify.py
pdb4amber/pdb4amber.py
pdb4amber/residue.py
pdb4amber/template.py
pdb4amber/utils.py
pdb4amber/visualizer.py
pdb4amber.egg-info/PKG-INFO
pdb4amber.egg-info/SOURCES.txt
pdb4amber.egg-info/dependency_links.txt
pdb4amber.egg-info/entry_points.txt
pdb4amber.egg-info/not-zip-safe
pdb4amber.egg-info/top_level.txt
pdb4amber/builder/__init__.py
pdb4amber/builder/builder.py
pdb4amber/builder/leap.py
pdb4amber/builder/nab.py
pdb4amber/builder/pytraj_build.py